LICENSE.txt
MANIFEST.in
README.rst
requirements.txt
setup.cfg
setup.py
versioneer.py
docs/source/api.rst
docs/source/changelog.rst
docs/source/index.rst
docs/source/install.rst
s3fs/__init__.py
s3fs/_version.py
s3fs/core.py
s3fs/errors.py
s3fs/mapping.py
s3fs/utils.py
s3fs/tests/__init__.py
s3fs/tests/test_mapping.py
s3fs/tests/test_s3fs.py
s3fs/tests/test_utils.py
s3fs_py36_backport.egg-info/PKG-INFO
s3fs_py36_backport.egg-info/SOURCES.txt
s3fs_py36_backport.egg-info/dependency_links.txt
s3fs_py36_backport.egg-info/not-zip-safe
s3fs_py36_backport.egg-info/requires.txt
s3fs_py36_backport.egg-info/top_level.txt