Metadata-Version: 2.1
Name: s3fs-py36-backport
Version: 0.6.0a1
Summary: s3fs backport to python 3.6
Home-page: http://github.com/isidentical-backports/s3fs/
License: BSD
Platform: UNKNOWN
Classifier: Development Status :: 4 - Beta
Classifier: Intended Audience :: Developers
Classifier: License :: OSI Approved :: BSD License
Classifier: Operating System :: OS Independent
Classifier: Programming Language :: Python :: 3.7
Classifier: Programming Language :: Python :: 3.8
Requires-Python: >= 3.6
Provides-Extra: awscli
Provides-Extra: boto3
